urbanopt_des/activity_to_osa/Gemfile
urbanopt_des/activity_to_osa/README.md
urbanopt_des/activity_to_osa/measures/AddMonthlyJSONUtilityData/LICENSE.md
urbanopt_des/activity_to_osa/measures/AddMonthlyJSONUtilityData/README.md
urbanopt_des/activity_to_osa/measures/AddMonthlyJSONUtilityData/README.md.erb
urbanopt_des/activity_to_osa/measures/AddMonthlyJSONUtilityData/measure.rb
urbanopt_des/activity_to_osa/measures/AddMonthlyJSONUtilityData/measure.xml
urbanopt_des/activity_to_osa/measures/AddMonthlyUtilityData/LICENSE.md
urbanopt_des/activity_to_osa/measures/AddMonthlyUtilityData/README.md
urbanopt_des/activity_to_osa/measures/AddMonthlyUtilityData/README.md.erb
urbanopt_des/activity_to_osa/measures/AddMonthlyUtilityData/measure.rb
urbanopt_des/activity_to_osa/measures/AddMonthlyUtilityData/measure.xml
urbanopt_des/activity_to_osa/measures/AddMonthlyUtilityData/tests/AddMonthlyUtilityData_Test.rb
urbanopt_des/activity_to_osa/measures/AddMonthlyUtilityData/tests/electric_billed_usages.json
urbanopt_des/activity_to_osa/measures/AddMonthlyUtilityData/tests/gas_billed_usages.json
urbanopt_des/activity_to_osa/measures/CalibrationReports/LICENSE.md
urbanopt_des/activity_to_osa/measures/CalibrationReports/README.md
urbanopt_des/activity_to_osa/measures/CalibrationReports/README.md.erb
urbanopt_des/activity_to_osa/measures/CalibrationReports/measure.rb
urbanopt_des/activity_to_osa/measures/CalibrationReports/measure.xml
urbanopt_des/activity_to_osa/measures/CalibrationReports/resources/report.html.in
urbanopt_des/activity_to_osa/measures/CalibrationReports/tests/CalibrationReports_Test.rb
urbanopt_des/activity_to_osa/measures/CalibrationReports/tests/ExampleModel.osm
urbanopt_des/activity_to_osa/measures/CalibrationReports/tests/ExampleModelNoDemandInput.osm
urbanopt_des/activity_to_osa/measures/CalibrationReports/tests/ExampleModelNoGasInput.osm
urbanopt_des/activity_to_osa/measures/CalibrationReports/tests/USA_CO_Golden-NREL.724666_TMY3.epw
urbanopt_des-0.2.0.dist-info/METADATA
urbanopt_des-0.2.0.dist-info/WHEEL
urbanopt_des-0.2.0.dist-info/entry_points.txt
urbanopt_des-0.2.0.dist-info/licenses/LICENSE.md
urbanopt_des-0.2.0.dist-info/RECORD
