Metadata-Version: 2.4
Name: urbanopt-des
Version: 0.2.0
Summary: 
License-File: LICENSE.md
Author: Nicholas Long
Author-email: nicholas.long@nlr.gov
Requires-Python: >=3.10,<3.14
Classifier: Programming Language :: Python :: 3
Classifier: Programming Language :: Python :: 3.10
Classifier: Programming Language :: Python :: 3.11
Classifier: Programming Language :: Python :: 3.12
Classifier: Programming Language :: Python :: 3.13
Requires-Dist: cyclopts (>=4.5.1,<5.0.0)
Requires-Dist: geojson-modelica-translator (>=0.13.0,<0.14.0)
Requires-Dist: geopandas (<1.0)
